methrandir/__init__.py
methrandir/methrandir.py
methrandir-0.1.2.dist-info/LICENSE
methrandir-0.1.2.dist-info/METADATA
methrandir-0.1.2.dist-info/WHEEL
methrandir-0.1.2.dist-info/entry_points.txt
methrandir-0.1.2.dist-info/top_level.txt
methrandir-0.1.2.dist-info/RECORD
