Metadata-Version: 2.1
Name: methrandir
Version: 0.1.2
Summary: Python utility for understanding whole genome bisulfite data and viewing it as a whole
Home-page: https://forgemia.inra.fr/skander.hatira/methrandir
Author: Skander Hatira
Author-email: skander.hatira@inrae.fr
License: UNKNOWN
Project-URL: Bug Tracker, https://forgemia.inra.fr/skander.hatira/methrandir/-/issues
Platform: UNKNOWN
Classifier: Programming Language :: Python :: 3
Classifier: License :: OSI Approved :: MIT License
Classifier: Operating System :: OS Independent
Requires-Python: >=3.8.5
License-File: LICENSE
Requires-Dist: scikit-learn
Requires-Dist: pandas
Requires-Dist: plotly
Requires-Dist: kaleido
Requires-Dist: seaborn
